[
  {
    "slug": "bioma-probiotics",
    "title": "Bioma Probiotics — Gut Health Support (US)",
    "desc": "Digestive health support for men & women. 3-in-1 formula with prebiotic XOS, tributyrin (postbiotic) and Bifidobacterium strains. Vegan, gluten-free; 60 delayed-release capsules (30-day supply).",
    "image": "/assets/img/products/bioma-probiotics/ini1.png",
    ""price": { "d": 26, "c": "14", "currency": "$" },
    "rating": 4.6,
    "reviews": "2k+",
    "swatches": ["#2ecc71", "#3498db", "#f39c12"],
    "countryNote": "Available: US",
    "productUrl": "/us/products/bioma-probiotics/",
    "goUrl": "/go/bioma-probiotics/?country=US"
  }
]
